pv_sizing/app_layout/__init__.py
pv_sizing/app_layout/applayout.py
pv_sizing/app_layout/dashboard.py
pv_sizing/dimension/__init__.py
pv_sizing/dimension/battery.py
pv_sizing/dimension/pv.py
pv_sizing/utils/__init__.py
pv_sizing/utils/constants.py
pv_sizing/utils/correct_data_experimental.py
pv_sizing/utils/irradiance.py
pv_sizing/utils/load_example.py
pv_sizing/utils/pv_utils.py
pv_sizing/utils/example_data/example_irr.csv
pv_sizing/utils/example_data/example_load.csv
pv_sizing/web_scrapping/__init__.py
pv_sizing/web_scrapping/electricity_price.py
pv_sizing/web_scrapping/irradiance.py
pv_sizing-1.1.2.dist-info/LICENSE.txt
pv_sizing-1.1.2.dist-info/METADATA
pv_sizing-1.1.2.dist-info/WHEEL
pv_sizing-1.1.2.dist-info/top_level.txt
pv_sizing-1.1.2.dist-info/RECORD
