Metadata-Version: 2.1
Name: pv-sizing
Version: 1.1.2
Home-page: https://github.com/brakisto/PV-sizing
Author: Kiril Ivanov Kurtev
Author-email: brakisto2015@gmail.com
License: MIT
Keywords: photovoltaic sizing batteries financial analysis
License-File: LICENSE.txt
Requires-Dist: numpy
Requires-Dist: numpy-financial
Requires-Dist: pandas
Requires-Dist: pvlib
Requires-Dist: selenium
Requires-Dist: plotly
Requires-Dist: dash
